planet_mcp/__init__.py
planet_mcp/clients.py
planet_mcp/main.py
planet_mcp/py.typed
planet_mcp/server.py
planet_mcp/servers/__init__.py
planet_mcp/servers/descriptions.py
planet_mcp/servers/sdk.py
planet_mcp/servers/tiles.py
planet_mcp-0.1.1.dist-info/licenses/LICENSE
planet_mcp-0.1.1.dist-info/WHEEL
planet_mcp-0.1.1.dist-info/entry_points.txt
planet_mcp-0.1.1.dist-info/METADATA
planet_mcp-0.1.1.dist-info/RECORD
