Metadata-Version: 2.4
Name: planet-mcp
Version: 0.1.1
License-Expression: Apache-2.0
License-File: LICENSE
Requires-Dist: aiocache>=0.12.3
Requires-Dist: fastmcp==2.12.4
Requires-Dist: planet>=3.0.0
Requires-Dist: uv
Requires-Dist: mercantile>=1.2.1
Requires-Python: >=3.11
